{
  "header": {
      "accept": "*/*",
      "store-id": "727",
      "user-id": "123",
      "Content-Type": "application/json"
    },
  "body": {
    "attendanceId":"string",
    "channel":"SMS",
    "message":"string",
    "messageId":"string",
    "messageParameters":{
      "additionalProp1":"string",
      "additionalProp2":"string",
      "additionalProp3":"string"
    },
    "messageTemplate":"REQUEST_FORMALIZATION",
    "messageType":"SIMPLE_TEXT",
    "receiverId":"string",
    "resend":true,
    "senderName":"string"
  }  
}